swag/__init__.py
swag/autoblog.py
swag/builder.py
swag/cli.py
swag/lorem.py
swag/resources.py
simple_swag-0.1.4.dist-info/METADATA
simple_swag-0.1.4.dist-info/WHEEL
simple_swag-0.1.4.dist-info/entry_points.txt
simple_swag-0.1.4.dist-info/top_level.txt
simple_swag-0.1.4.dist-info/RECORD
