Metadata-Version: 2.1
Name: simple-swag
Version: 0.1.4
Summary: "Simple Website Auto Generator"
Home-page: https://github.com/peterprescott/simple-swag
Author: Peter Prescott
Author-email: prescott.peter@gmail.com
Project-URL: Bug Tracker, https://github.com/peterprescott/simple-swag/issues
Requires-Python: >=3.6
Requires-Dist: fire
Requires-Dist: lorem
Requires-Dist: markdown
Requires-Dist: markdown-full-yaml-metadata
Requires-Dist: multiavatar
Requires-Dist: pandas
Requires-Dist: Pygments
Requires-Dist: unidecode
